pellet/__init__.py
pellet/middleware.py
pellet/utils.py
pellet-0.1.3.dist-info/LICENSE
pellet-0.1.3.dist-info/WHEEL
pellet-0.1.3.dist-info/METADATA
pellet-0.1.3.dist-info/RECORD
