Metadata-Version: 2.1
Name: pellet
Version: 0.1.3
Summary: Pellet helps improve your Django app performance by discovering N+1 queries
Home-page: https://github.com/har777/pellet
License: BSD-3-Clause
Keywords: django,python,performance,database,N+1
Author: Harikrishnan Shaji
Author-email: hihari777@gmail.com
Requires-Python: >=3.8,<4.0
Classifier: License :: OSI Approved :: BSD License
Classifier: Programming Language :: Python :: 3
Classifier: Programming Language :: Python :: 3.10
Classifier: Programming Language :: Python :: 3.8
Classifier: Programming Language :: Python :: 3.9
Requires-Dist: rich (==12.5.1)
Project-URL: Documentation, https://github.com/har777/pellet
Project-URL: Repository, https://github.com/har777/pellet
